lightning_api_access/APIAccessFrontend.py
lightning_api_access/__init__.py
lightning_api_access/ui/craco.config.js
lightning_api_access/ui/yarn.lock
lightning_api_access/ui/@types/index.d.ts
lightning_api_access/ui/build/favicon.svg
lightning_api_access/ui/build/index.html
lightning_api_access/ui/build/robots.txt
lightning_api_access/ui/build/static/css/main.d4db2813.css
lightning_api_access/ui/build/static/css/main.d4db2813.css.map
lightning_api_access/ui/build/static/js/787.9615c779.chunk.js
lightning_api_access/ui/build/static/js/787.9615c779.chunk.js.map
lightning_api_access/ui/build/static/js/main.5baf4a10.js
lightning_api_access/ui/build/static/js/main.5baf4a10.js.LICENSE.txt
lightning_api_access/ui/build/static/js/main.5baf4a10.js.map
lightning_api_access/ui/build/static/media/UCity-Light.8352e423a843d9a0c52a.otf
lightning_api_access/ui/build/static/media/UCity-Regular.e28f5006c1976d08baaa.otf
lightning_api_access/ui/build/static/media/UCity-Semibold.b37489cc447430fe4ba7.otf
lightning_api_access/ui/build/static/media/error.11892047d0183a4723b91dc0fb98cb95.svg
lightning_api_access/ui/build/static/media/success.5edae4c5b171e2c1c5a3c54273c47ba8.svg
lightning_api_access/ui/build/static/media/warning.5c542673e84e77ceb6a230bfea7f7263.svg
lightning_api_access/ui/public/favicon.svg
lightning_api_access/ui/public/index.html
lightning_api_access/ui/public/robots.txt
lightning_api_access/ui/src/App.tsx
lightning_api_access/ui/src/index.css
lightning_api_access/ui/src/index.tsx
lightning_api_access/ui/src/reportWebVitals.ts
lightning_api_access/ui/src/utils.ts
lightning_api_access-0.0.5.dist-info/LICENSE
lightning_api_access-0.0.5.dist-info/METADATA
lightning_api_access-0.0.5.dist-info/WHEEL
lightning_api_access-0.0.5.dist-info/top_level.txt
lightning_api_access-0.0.5.dist-info/RECORD
